PySimpleGUI/PySimpleGUI.py
PySimpleGUI/__init__.py
xl_gui-4.60.5.dist-info/licenses/LICENSE
xl_gui-4.60.5.dist-info/METADATA
xl_gui-4.60.5.dist-info/WHEEL
xl_gui-4.60.5.dist-info/entry_points.txt
xl_gui-4.60.5.dist-info/top_level.txt
xl_gui-4.60.5.dist-info/RECORD
