Metadata-Version: 2.4
Name: xl-gui
Version: 4.60.5
Summary: A freely available version of PySimpleGUI 4.60.5, published for continued community use after official support ended
Home-page: https://github.com/XL1126/XL-GUI
Author: XL1126
Author-email: 258233740@qq.com
Keywords: GUI UI tkinter simple easy beginner graphics
Classifier: Programming Language :: Python :: 3
Classifier: Programming Language :: Python :: 3.6
Classifier: Programming Language :: Python :: 3.7
Classifier: Programming Language :: Python :: 3.8
Classifier: Programming Language :: Python :: 3.9
Classifier: Programming Language :: Python :: 3.10
Classifier: Programming Language :: Python :: 3.11
Classifier: Programming Language :: Python :: 3.12
Classifier: License :: OSI Approved :: GNU Lesser General Public License v3 or later (LGPLv3+)
Classifier: Topic :: Multimedia :: Graphics
Classifier: Operating System :: OS Independent
Requires-Python: >=3.6
License-File: LICENSE
Dynamic: author
Dynamic: author-email
Dynamic: classifier
Dynamic: description
Dynamic: description-content-type
Dynamic: home-page
Dynamic: keywords
Dynamic: license-file
Dynamic: requires-python
Dynamic: summary
